CHANGES.txt
LICENSE.txt
MANIFEST.in
README.txt
bootstrap.py
buildout.cfg
setup.py
src/p01/__init__.py
src/p01.form.egg-info/PKG-INFO
src/p01.form.egg-info/SOURCES.txt
src/p01.form.egg-info/dependency_links.txt
src/p01.form.egg-info/namespace_packages.txt
src/p01.form.egg-info/not-zip-safe
src/p01.form.egg-info/requires.txt
src/p01.form.egg-info/top_level.txt
src/p01/form/__init__.py
src/p01/form/configure.zcml
src/p01/form/interfaces.py
src/p01/form/layer.py
src/p01/form/form/README.txt
src/p01/form/form/__init__.py
src/p01/form/form/browser.zcml
src/p01/form/form/btn.py
src/p01/form/form/btn.zcml
src/p01/form/form/btn_display.pt
src/p01/form/form/btn_input.pt
src/p01/form/form/configure.zcml
src/p01/form/form/form-display.pt
src/p01/form/form/form.pt
src/p01/form/form/form.py
src/p01/form/form/subform-layout.pt
src/p01/form/form/subform.pt
src/p01/form/widget/__init__.py
src/p01/form/widget/checkbox.py
src/p01/form/widget/checkbox.zcml
src/p01/form/widget/checkbox_display.pt
src/p01/form/widget/checkbox_hidden.pt
src/p01/form/widget/checkbox_input.pt
src/p01/form/widget/checkbox_input_div.pt
src/p01/form/widget/checkbox_single_input.pt
src/p01/form/widget/checkbox_single_input_div.pt
src/p01/form/widget/configure.zcml
src/p01/form/widget/dictionary.py
src/p01/form/widget/dictionary.txt
src/p01/form/widget/dictionary.zcml
src/p01/form/widget/file.py
src/p01/form/widget/file.zcml
src/p01/form/widget/file_display.pt
src/p01/form/widget/file_input.pt
src/p01/form/widget/password.py
src/p01/form/widget/password.txt
src/p01/form/widget/password.zcml
src/p01/form/widget/password_confirmation_input.pt
src/p01/form/widget/password_display.pt
src/p01/form/widget/password_input.pt
src/p01/form/widget/radio.py
src/p01/form/widget/radio.zcml
src/p01/form/widget/radio_display.pt
src/p01/form/widget/radio_hidden.pt
src/p01/form/widget/radio_input.pt
src/p01/form/widget/radio_input_div.pt
src/p01/form/widget/select.py
src/p01/form/widget/select.zcml
src/p01/form/widget/select_display.pt
src/p01/form/widget/select_hidden.pt
src/p01/form/widget/select_input.pt
src/p01/form/widget/select_optgroup_input.pt
src/p01/form/widget/tests.py
src/p01/form/widget/text.py
src/p01/form/widget/text.zcml
src/p01/form/widget/text_display.pt
